<package>
  <description brief="pykdl_utils">

    pykdl_utils contains kdl_parser.py, for parsing URDF objects
     from the robot_model_py stack into PyKDL trees and chains, 
     and kdl_kinematics.py, for wrapping KDL kinematics calls, making
     kinematics requests in Python far simpler.  jointspace_kdl_kin.py
     also contains a KDLKinematics superclass which subscribes to /joint_states,
     automatically filling the FK and jacobian requests with the current joint
     angles.

  </description>
  <author>Kelsey Hawkins / kphawkins@gatech.edu, Advisor: Prof. Charlie Kemp (Healthcare Robotics Lab at Georgia Tech)</author>
  <license>BSD</license>
  <review status="unreviewed" notes=""/>
  <url>http://ros.org/wiki/pykdl_utils</url>
  <depend package="rospy"/>
  <depend package="tf"/>
  <depend package="geometry_msgs"/>
  <depend package="sensor_msgs"/>
  <depend package="hrl_geom"/>
  <depend package="urdf_parser_py"/>
  <depend package="python_orocos_kdl"/>

</package>


